sphinxcontrib/applehelp/__init__.py
sphinxcontrib/applehelp/locales/sphinxcontrib.applehelp.pot
sphinxcontrib/applehelp/locales/.tx/config
sphinxcontrib/applehelp/locales/ar/LC_MESSAGES/sphinxcontrib.applehelp.mo
sphinxcontrib/applehelp/locales/ar/LC_MESSAGES/sphinxcontrib.applehelp.po
sphinxcontrib/applehelp/locales/bn/LC_MESSAGES/sphinxcontrib.applehelp.mo
sphinxcontrib/applehelp/locales/bn/LC_MESSAGES/sphinxcontrib.applehelp.po
sphinxcontrib/applehelp/locales/ca/LC_MESSAGES/sphinxcontrib.applehelp.mo
sphinxcontrib/applehelp/locales/ca/LC_MESSAGES/sphinxcontrib.applehelp.po
sphinxcontrib/applehelp/locales/cak/LC_MESSAGES/sphinxcontrib.applehelp.mo
sphinxcontrib/applehelp/locales/cak/LC_MESSAGES/sphinxcontrib.applehelp.po
sphinxcontrib/applehelp/locales/cs/LC_MESSAGES/sphinxcontrib.applehelp.mo
sphinxcontrib/applehelp/locales/cs/LC_MESSAGES/sphinxcontrib.applehelp.po
sphinxcontrib/applehelp/locales/cy/LC_MESSAGES/sphinxcontrib.applehelp.mo
sphinxcontrib/applehelp/locales/cy/LC_MESSAGES/sphinxcontrib.applehelp.po
sphinxcontrib/applehelp/locales/da/LC_MESSAGES/sphinxcontrib.applehelp.mo
sphinxcontrib/applehelp/locales/da/LC_MESSAGES/sphinxcontrib.applehelp.po
sphinxcontrib/applehelp/locales/de/LC_MESSAGES/sphinxcontrib.applehelp.mo
sphinxcontrib/applehelp/locales/de/LC_MESSAGES/sphinxcontrib.applehelp.po
sphinxcontrib/applehelp/locales/el/LC_MESSAGES/sphinxcontrib.applehelp.mo
sphinxcontrib/applehelp/locales/el/LC_MESSAGES/sphinxcontrib.applehelp.po
sphinxcontrib/applehelp/locales/eo/LC_MESSAGES/sphinxcontrib.applehelp.mo
sphinxcontrib/applehelp/locales/eo/LC_MESSAGES/sphinxcontrib.applehelp.po
sphinxcontrib/applehelp/locales/es/LC_MESSAGES/sphinxcontrib.applehelp.mo
sphinxcontrib/applehelp/locales/es/LC_MESSAGES/sphinxcontrib.applehelp.po
sphinxcontrib/applehelp/locales/et/LC_MESSAGES/sphinxcontrib.applehelp.mo
sphinxcontrib/applehelp/locales/et/LC_MESSAGES/sphinxcontrib.applehelp.po
sphinxcontrib/applehelp/locales/eu/LC_MESSAGES/sphinxcontrib.applehelp.mo
sphinxcontrib_applehelp-1.0.5.dist-info/LICENSE
sphinxcontrib_applehelp-1.0.5.dist-info/WHEEL
sphinxcontrib_applehelp-1.0.5.dist-info/METADATA
sphinxcontrib_applehelp-1.0.5.dist-info/RECORD
